robot_format_converter/__init__.py
robot_format_converter/__main__.py
robot_format_converter/core.py
robot_format_converter/exporters.py
robot_format_converter/parsers.py
robot_format_converter/schema.py
robot_format_converter/utils.py
robot_format_converter-1.0.0.dist-info/licenses/LICENSE
robot_format_converter-1.0.0.dist-info/METADATA
robot_format_converter-1.0.0.dist-info/WHEEL
robot_format_converter-1.0.0.dist-info/entry_points.txt
robot_format_converter-1.0.0.dist-info/top_level.txt
robot_format_converter-1.0.0.dist-info/RECORD
