Metadata-Version: 2.4
Name: robot-format-converter
Version: 1.0.0
Summary: Universal robot description format converter
Author-email: Thanh Nguyen <thanh.nguyen@example.com>
Maintainer-email: Thanh Nguyen <thanh.nguyen@example.com>
License: Apache-2.0
Project-URL: Homepage, https://github.com/thanhndv212/robot_format_converter
Project-URL: Repository, https://github.com/thanhndv212/robot_format_converter.git
Project-URL: Documentation, https://github.com/thanhndv212/robot_format_converter#readme
Project-URL: Bug Reports, https://github.com/thanhndv212/robot_format_converter/issues
Keywords: robotics,urdf,sdf,mjcf,robot-description,format-conversion,robot-modeling
Classifier: Development Status :: 4 - Beta
Classifier: Intended Audience :: Developers
Classifier: Intended Audience :: Science/Research
Classifier: License :: OSI Approved :: Apache Software License
Classifier: Operating System :: OS Independent
Classifier: Programming Language :: Python :: 3
Classifier: Programming Language :: Python :: 3.8
Classifier: Programming Language :: Python :: 3.9
Classifier: Programming Language :: Python :: 3.10
Classifier: Programming Language :: Python :: 3.11
Classifier: Programming Language :: Python :: 3.12
Classifier: Topic :: Scientific/Engineering :: Artificial Intelligence
Classifier: Topic :: Software Development :: Libraries :: Python Modules
Requires-Python: >=3.8
License-File: LICENSE
Requires-Dist: numpy>=1.20.0
Requires-Dist: lxml>=4.6.0
Requires-Dist: pyyaml>=5.4.0
Requires-Dist: jsonschema>=3.2.0
Requires-Dist: click>=8.0.0
Provides-Extra: dev
Requires-Dist: pytest>=6.0; extra == "dev"
Requires-Dist: pytest-cov>=2.10.0; extra == "dev"
Requires-Dist: black>=21.0.0; extra == "dev"
Requires-Dist: isort>=5.0.0; extra == "dev"
Requires-Dist: flake8>=3.8.0; extra == "dev"
Requires-Dist: mypy>=0.800; extra == "dev"
Requires-Dist: pre-commit>=2.10.0; extra == "dev"
Provides-Extra: docs
Requires-Dist: sphinx>=4.0.0; extra == "docs"
Requires-Dist: sphinx-rtd-theme>=0.5.0; extra == "docs"
Requires-Dist: sphinx-autodoc-typehints>=1.11.0; extra == "docs"
Provides-Extra: all
Requires-Dist: robot-format-converter[dev,docs]; extra == "all"
Dynamic: license-file
